LICENSE
aiogh/__init__.py
aiogh/github.py
aiogh/types.py
aiogh-0.1.2.dist-info/LICENSE
aiogh-0.1.2.dist-info/WHEEL
aiogh-0.1.2.dist-info/METADATA
aiogh-0.1.2.dist-info/RECORD
